dev/__init__.py
dev/pos_commonness.py
export/__init__.py
export/export_grammar.py
export/tagged_words.py
randomsentence/__init__.py
randomsentence/brown.py
randomsentence/dir.py
randomsentence/google-10000-english.txt
randomsentence/grammar_check.py
randomsentence/keyword.py
randomsentence/ngram.py
randomsentence/randomsentence.py
randomsentence/sentence.py
randomsentence/sentence_maker.py
randomsentence/sentence_tools.py
randomsentence/utils.py
randomsentence/word.py
randomsentence/database/google-10000-english.txt
randomsentence/database/settings.yaml
randomsentence/database/words.txt
randomsentence-0.3.1.dist-info/METADATA
randomsentence-0.3.1.dist-info/RECORD
randomsentence-0.3.1.dist-info/WHEEL
randomsentence-0.3.1.dist-info/top_level.txt
