Metadata-Version: 2.1
Name: randomsentence
Version: 0.3.1
Summary: Generate a sentence, randomly or from a list of keywords/initials. This is based on Brown corpus.
Home-page: https://github.com/patarapolw/randomsentence
Author: Pacharapol Withayasakpunt
Author-email: patarapolw@gmail.com
License: MIT
Keywords: random sentence random_sentence random_word
Platform: UNKNOWN
Classifier: Environment :: Console
Classifier: Intended Audience :: Developers
Classifier: License :: OSI Approved :: MIT License
Classifier: Natural Language :: English
Classifier: Programming Language :: Python :: 3.5
Classifier: Programming Language :: Python :: 3.6
Classifier: Topic :: Utilities
Requires-Python: >=3.5
Provides-Extra: test
Provides-Extra: with-language-check
Requires-Dist: nltk
Requires-Dist: markovify
Requires-Dist: mosestokenizer
Provides-Extra: test
Requires-Dist: pytest; extra == 'test'
Requires-Dist: pytest-xdist; extra == 'test'
Requires-Dist: pytest-repeat; extra == 'test'
Requires-Dist: pytest-timeout; extra == 'test'
Requires-Dist: pytest-doctestplus; extra == 'test'
Provides-Extra: with-language-check
Requires-Dist: language-check; extra == 'with-language-check'
